pyhist/__init__.py
pyhist/cli.py
pyhist/pyhist.py
pyhist/history/__init__.py
pyhist/history/git_history.py
pyhist/history/history.py
pyhist/history/history_exception.py
pyhist/history/pyhist_item.py
pyhist/io/__init__.py
pyhist/io/changelog_generator.py
pyhist/io/setup_parser.py
pyhist/tests/__init__.py
pyhist/tests/integration/__init__.py
pyhist/tests/integration/test_git_history.py
pyhist/tests/integration/test_history.py
pyhist/tests/integration/test_setup_parser.py
pyhist/tests/unit/__init__.py
pyhist/tests/unit/test_pyhist.py
pyhist/tests/unit/test_semantic_versioning.py
pyhist/tests/validation/__init__.py
pyhist/tests/validation/base_validation_test.py
pyhist/tests/validation/test_cli_init.py
pyhist/tests/validation/test_cli_major.py
pyhist/tests/validation/test_cli_update.py
pyhist/versioning/__init__.py
pyhist/versioning/commit_type.py
pyhist/versioning/semantic_versioning.py
pyhist/versioning/version.py
pyhist/versioning/version_exception.py
pyhist-0.0.5.dist-info/LICENSE
pyhist-0.0.5.dist-info/METADATA
pyhist-0.0.5.dist-info/WHEEL
pyhist-0.0.5.dist-info/entry_points.txt
pyhist-0.0.5.dist-info/top_level.txt
pyhist-0.0.5.dist-info/RECORD
