Metadata-Version: 2.1
Name: pyhist
Version: 0.0.5
Summary: UNKNOWN
Home-page: https://github.com/jgoodman8/pyhist
Author: Javier Guzman
Author-email: jguzmanfd@gmail.com
License: Apache Software License
Platform: UNKNOWN
Requires-Dist: click (==7.1.2)
Requires-Dist: GitPython (==3.1.1)
Provides-Extra: tests
Requires-Dist: black (==19.10b0) ; extra == 'tests'
Requires-Dist: pre-commit (==2.5.1) ; extra == 'tests'
Requires-Dist: pytest (==5.4.2) ; extra == 'tests'
